cellworld_npx/__init__.py
cellworld_npx/backup.py
cellworld_npx/behavior.py
cellworld_npx/binning.py
cellworld_npx/camera.py
cellworld_npx/celltile.py
cellworld_npx/classifier.py
cellworld_npx/cluster_metrics.py
cellworld_npx/coverage.py
cellworld_npx/decoder.py
cellworld_npx/episode.py
cellworld_npx/io.py
cellworld_npx/kalman.py
cellworld_npx/lfp.py
cellworld_npx/map.py
cellworld_npx/neural_decoders.py
cellworld_npx/pose.py
cellworld_npx/probe.py
cellworld_npx/recording.py
cellworld_npx/state_decoder.py
cellworld_npx/sync.py
cellworld_npx/utils.py
cellworld_npx-0.0.6.dist-info/LICENSE.txt
cellworld_npx-0.0.6.dist-info/METADATA
cellworld_npx-0.0.6.dist-info/WHEEL
cellworld_npx-0.0.6.dist-info/top_level.txt
cellworld_npx-0.0.6.dist-info/RECORD
