Metadata-Version: 2.1
Name: cellworld_npx
Version: 0.0.6
Summary: Dombeck/MacIver labs neuroethology analysis package - combined cellworld behavior and neuropixels recordings
Author: Chris Angeloni
Author-email: chris.angeloni@gmail.com
License: MIT
License-File: LICENSE.txt
Requires-Dist: numpy
Requires-Dist: scipy
Requires-Dist: matplotlib
Requires-Dist: json-cpp
Requires-Dist: cellworld
Requires-Dist: npyx
Requires-Dist: pandas
Requires-Dist: astropy
Requires-Dist: rtree
Requires-Dist: kilosort
Requires-Dist: torch
Requires-Dist: filterpy
Requires-Dist: opencv-python
Requires-Dist: tables
Provides-Extra: kilosort
Requires-Dist: kilosort; extra == "kilosort"
